[
  {
    "inputUrl": "https://www.instagram.com/sugirbaydastan",
    "id": "6837907099",
    "username": "sugirbaydastan",
    "url": "https://www.instagram.com/sugirbaydastan",
    "fullName": "Dastish",
    "biography": "",
    "externalUrls": [],
    "followersCount": 436,
    "followsCount": 438,
    "hasChannel": false,
    "highlightReelCount": 0,
    "isBusinessAccount": false,
    "joinedRecently": false,
    "businessCategoryName": "Personal blog",
    "private": false,
    "verified": false,
    "profilePicUrl": "https://instagram.fcgh3-2.fna.fbcdn.net/v/t51.2885-19/450098421_490518190002003_8871821147112128027_n.jpg?stp=dst-jpg_e0_s150x150_tt6&_nc_ht=instagram.fcgh3-2.fna.fbcdn.net&_nc_cat=103&_nc_oc=Q6cZ2QF9sx0JDkrugwONNHmykgsO5mMA-Mci8Y6peX8Lbx1-6beXS5MWofDZ6xNi6TkiNqw&_nc_ohc=c8RBXcfhrtEQ7kNvwFxPAC0&_nc_gid=Y1wez7Z7yzDjmAY2sS7_JA&edm=AOQ1c0wBAAAA&ccb=7-5&oh=00_AfONSZEe59G5zYuT7rg2XK1lsAJCcxJzGc6WBkzyj52mAA&oe=68643AA0&_nc_sid=8b3546",
    "profilePicUrlHD": "https://instagram.fcgh3-2.fna.fbcdn.net/v/t51.2885-19/450098421_490518190002003_8871821147112128027_n.jpg?stp=dst-jpg_s320x320_tt6&_nc_ht=instagram.fcgh3-2.fna.fbcdn.net&_nc_cat=103&_nc_oc=Q6cZ2QF9sx0JDkrugwONNHmykgsO5mMA-Mci8Y6peX8Lbx1-6beXS5MWofDZ6xNi6TkiNqw&_nc_ohc=c8RBXcfhrtEQ7kNvwFxPAC0&_nc_gid=Y1wez7Z7yzDjmAY2sS7_JA&edm=AOQ1c0wBAAAA&ccb=7-5&oh=00_AfPh57hEzTdL6swZ3FSV9fTQs-c9uRDXmrWGuvGBVo8kVA&oe=68643AA0&_nc_sid=8b3546",
    "igtvVideoCount": 0,
    "relatedProfiles": [],
    "latestIgtvVideos": [],
    "postsCount": 5,
    "latestPosts": [
      {
        "id": "3196187369005995623",
        "type": "Sidecar",
        "shortCode": "CxbI3pdMVZn",
        "caption": "",
        "hashtags": [],
        "mentions": [],
        "url": "https://www.instagram.com/p/CxbI3pdMVZn/",
        "commentsCount": 25,
        "dimensionsHeight": 1143,
        "dimensionsWidth": 1080,
        "displayUrl": "https://instagram.fcgh3-1.fna.fbcdn.net/v/t51.29350-15/380449691_158125947346418_6755509034203888121_n.jpg?stp=dst-jpg_e35_p1080x1080_tt6&_nc_ht=instagram.fcgh3-1.fna.fbcdn.net&_nc_cat=102&_nc_oc=Q6cZ2QF9sx0JDkrugwONNHmykgsO5mMA-Mci8Y6peX8Lbx1-6beXS5MWofDZ6xNi6TkiNqw&_nc_ohc=4v9H46AsCWAQ7kNvwHGqVsl&_nc_gid=Y1wez7Z7yzDjmAY2sS7_JA&edm=AOQ1c0wBAAAA&ccb=7-5&ig_cache_key=MzE5NjE4NzM2NDI3NDk4MjkxNA%3D%3D.3-ccb7-5&oh=00_AfM00YrrDtYe4OwMzdCanqU43ttK9K1Fb9z-w1i_NfXXkA&oe=686430C1&_nc_sid=8b3546",
        "images": [
          "https://instagram.fcgh3-1.fna.fbcdn.net/v/t51.29350-15/380449691_158125947346418_6755509034203888121_n.jpg?stp=dst-jpg_e35_p1080x1080_tt6&_nc_ht=instagram.fcgh3-1.fna.fbcdn.net&_nc_cat=102&_nc_oc=Q6cZ2QF9sx0JDkrugwONNHmykgsO5mMA-Mci8Y6peX8Lbx1-6beXS5MWofDZ6xNi6TkiNqw&_nc_ohc=4v9H46AsCWAQ7kNvwHGqVsl&_nc_gid=Y1wez7Z7yzDjmAY2sS7_JA&edm=AOQ1c0wBAAAA&ccb=7-5&ig_cache_key=MzE5NjE4NzM2NDI3NDk4MjkxNA%3D%3D.3-ccb7-5&oh=00_AfM00YrrDtYe4OwMzdCanqU43ttK9K1Fb9z-w1i_NfXXkA&oe=686430C1&_nc_sid=8b3546",
          "https://instagram.fcgh3-1.fna.fbcdn.net/v/t51.29350-15/379592129_860162285716415_9097639309236420120_n.jpg?stp=dst-jpg_e35_p1080x1080_tt6&_nc_ht=instagram.fcgh3-1.fna.fbcdn.net&_nc_cat=111&_nc_oc=Q6cZ2QF9sx0JDkrugwONNHmykgsO5mMA-Mci8Y6peX8Lbx1-6beXS5MWofDZ6xNi6TkiNqw&_nc_ohc=bSiuRg6ctawQ7kNvwEnOaKA&_nc_gid=Y1wez7Z7yzDjmAY2sS7_JA&edm=AOQ1c0wBAAAA&ccb=7-5&ig_cache_key=MzE5NjE4NzM2NDI2NjQxMDg5NA%3D%3D.3-ccb7-5&oh=00_AfPhwMdxnN_xwrIXzWmq-0JYfGYgwmIV5fg1YV2UX604Yg&oe=686439AA&_nc_sid=8b3546",
          "https://instagram.fcgh3-2.fna.fbcdn.net/v/t51.29350-15/381002025_690532543111167_5065084408412793915_n.jpg?stp=dst-jpg_e35_p1080x1080_tt6&_nc_ht=instagram.fcgh3-2.fna.fbcdn.net&_nc_cat=103&_nc_oc=Q6cZ2QF9sx0JDkrugwONNHmykgsO5mMA-Mci8Y6peX8Lbx1-6beXS5MWofDZ6xNi6TkiNqw&_nc_ohc=ZGEfq2AcxWQQ7kNvwHpRGIE&_nc_gid=Y1wez7Z7yzDjmAY2sS7_JA&edm=AOQ1c0wBAAAA&ccb=7-5&ig_cache_key=MzE5NjE4NzM2NDI3NDgzNDg5OA%3D%3D.3-ccb7-5&oh=00_AfNl8gMzGmKzZBFcbpw_aawd9wfqIqr1fgKyaqmKe025rg&oe=68643FF7&_nc_sid=8b3546",
          "https://instagram.fcgh3-1.fna.fbcdn.net/v/t51.29350-15/380255427_6522079627889095_4957130720950170090_n.jpg?stp=dst-jpg_e35_p1080x1080_tt6&_nc_ht=instagram.fcgh3-1.fna.fbcdn.net&_nc_cat=107&_nc_oc=Q6cZ2QF9sx0JDkrugwONNHmykgsO5mMA-Mci8Y6peX8Lbx1-6beXS5MWofDZ6xNi6TkiNqw&_nc_ohc=u_udxm-j5OUQ7kNvwFeCulT&_nc_gid=Y1wez7Z7yzDjmAY2sS7_JA&edm=AOQ1c0wBAAAA&ccb=7-5&ig_cache_key=MzE5NjE4NzM2NDI2NjUwNzEwNQ%3D%3D.3-ccb7-5&oh=00_AfOLV9EnpQ9w8bV8U_6x-W0L1BSnGotkrboXCGG1S6jNsg&oe=68641B9B&_nc_sid=8b3546"
        ],
        "alt": "Photo by Dastish on September 20, 2023.",
        "likesCount": 115,
        "timestamp": "2023-09-20T18:40:47.000Z",
        "childPosts": [
          {
            "id": "3196187364274982914",
            "type": "Image",
            "shortCode": "CxbI3lDM9AC",
            "caption": "",
            "hashtags": [],
            "mentions": [],
            "url": "https://www.instagram.com/p/CxbI3lDM9AC/",
            "commentsCount": 0,
            "firstComment": "",
            "latestComments": [],
            "dimensionsHeight": 1143,
            "dimensionsWidth": 1080,
            "displayUrl": "https://instagram.fcgh3-1.fna.fbcdn.net/v/t51.29350-15/380449691_158125947346418_6755509034203888121_n.jpg?stp=dst-jpg_e35_p1080x1080_tt6&_nc_ht=instagram.fcgh3-1.fna.fbcdn.net&_nc_cat=102&_nc_oc=Q6cZ2QF9sx0JDkrugwONNHmykgsO5mMA-Mci8Y6peX8Lbx1-6beXS5MWofDZ6xNi6TkiNqw&_nc_ohc=4v9H46AsCWAQ7kNvwHGqVsl&_nc_gid=Y1wez7Z7yzDjmAY2sS7_JA&edm=AOQ1c0wBAAAA&ccb=7-5&ig_cache_key=MzE5NjE4NzM2NDI3NDk4MjkxNA%3D%3D.3-ccb7-5&oh=00_AfM00YrrDtYe4OwMzdCanqU43ttK9K1Fb9z-w1i_NfXXkA&oe=686430C1&_nc_sid=8b3546",
            "images": [],
            "alt": "Photo by Dastish on September 20, 2023.",
            "likesCount": null,
            "timestamp": null,
            "childPosts": [],
            "ownerUsername": "sugirbaydastan",
            "ownerId": "6837907099"
          },
          {
            "id": "3196187364266410894",
            "type": "Image",
            "shortCode": "CxbI3lCsQOO",
            "caption": "",
            "hashtags": [],
            "mentions": [],
            "url": "https://www.instagram.com/p/CxbI3lCsQOO/",
            "commentsCount": 0,
            "firstComment": "",
            "latestComments": [],
            "dimensionsHeight": 1143,
            "dimensionsWidth": 1080,
            "displayUrl": "https://instagram.fcgh3-1.fna.fbcdn.net/v/t51.29350-15/379592129_860162285716415_9097639309236420120_n.jpg?stp=dst-jpg_e35_p1080x1080_tt6&_nc_ht=instagram.fcgh3-1.fna.fbcdn.net&_nc_cat=111&_nc_oc=Q6cZ2QF9sx0JDkrugwONNHmykgsO5mMA-Mci8Y6peX8Lbx1-6beXS5MWofDZ6xNi6TkiNqw&_nc_ohc=bSiuRg6ctawQ7kNvwEnOaKA&_nc_gid=Y1wez7Z7yzDjmAY2sS7_JA&edm=AOQ1c0wBAAAA&ccb=7-5&ig_cache_key=MzE5NjE4NzM2NDI2NjQxMDg5NA%3D%3D.3-ccb7-5&oh=00_AfPhwMdxnN_xwrIXzWmq-0JYfGYgwmIV5fg1YV2UX604Yg&oe=686439AA&_nc_sid=8b3546",
            "images": [],
            "alt": "Photo by Dastish on September 20, 2023.",
            "likesCount": null,
            "timestamp": null,
            "childPosts": [],
            "ownerUsername": "sugirbaydastan",
            "ownerId": "6837907099"
          },
          {
            "id": "3196187364274834898",
            "type": "Image",
            "shortCode": "CxbI3lDMY3S",
            "caption": "",
            "hashtags": [],
            "mentions": [],
            "url": "https://www.instagram.com/p/CxbI3lDMY3S/",
            "commentsCount": 0,
            "firstComment": "",
            "latestComments": [],
            "dimensionsHeight": 1143,
            "dimensionsWidth": 1080,
            "displayUrl": "https://instagram.fcgh3-2.fna.fbcdn.net/v/t51.29350-15/381002025_690532543111167_5065084408412793915_n.jpg?stp=dst-jpg_e35_p1080x1080_tt6&_nc_ht=instagram.fcgh3-2.fna.fbcdn.net&_nc_cat=103&_nc_oc=Q6cZ2QF9sx0JDkrugwONNHmykgsO5mMA-Mci8Y6peX8Lbx1-6beXS5MWofDZ6xNi6TkiNqw&_nc_ohc=ZGEfq2AcxWQQ7kNvwHpRGIE&_nc_gid=Y1wez7Z7yzDjmAY2sS7_JA&edm=AOQ1c0wBAAAA&ccb=7-5&ig_cache_key=MzE5NjE4NzM2NDI3NDgzNDg5OA%3D%3D.3-ccb7-5&oh=00_AfNl8gMzGmKzZBFcbpw_aawd9wfqIqr1fgKyaqmKe025rg&oe=68643FF7&_nc_sid=8b3546",
            "images": [],
            "alt": "Photo by Dastish on September 20, 2023.",
            "likesCount": null,
            "timestamp": null,
            "childPosts": [],
            "ownerUsername": "sugirbaydastan",
            "ownerId": "6837907099"
          },
          {
            "id": "3196187364266507105",
            "type": "Image",
            "shortCode": "CxbI3lCsnth",
            "caption": "",
            "hashtags": [],
            "mentions": [],
            "url": "https://www.instagram.com/p/CxbI3lCsnth/",
            "commentsCount": 0,
            "firstComment": "",
            "latestComments": [],
            "dimensionsHeight": 1142,
            "dimensionsWidth": 1080,
            "displayUrl": "https://instagram.fcgh3-1.fna.fbcdn.net/v/t51.29350-15/380255427_6522079627889095_4957130720950170090_n.jpg?stp=dst-jpg_e35_p1080x1080_tt6&_nc_ht=instagram.fcgh3-1.fna.fbcdn.net&_nc_cat=107&_nc_oc=Q6cZ2QF9sx0JDkrugwONNHmykgsO5mMA-Mci8Y6peX8Lbx1-6beXS5MWofDZ6xNi6TkiNqw&_nc_ohc=u_udxm-j5OUQ7kNvwFeCulT&_nc_gid=Y1wez7Z7yzDjmAY2sS7_JA&edm=AOQ1c0wBAAAA&ccb=7-5&ig_cache_key=MzE5NjE4NzM2NDI2NjUwNzEwNQ%3D%3D.3-ccb7-5&oh=00_AfOLV9EnpQ9w8bV8U_6x-W0L1BSnGotkrboXCGG1S6jNsg&oe=68641B9B&_nc_sid=8b3546",
            "images": [],
            "alt": "Photo by Dastish on September 20, 2023.",
            "likesCount": null,
            "timestamp": null,
            "childPosts": [],
            "ownerUsername": "sugirbaydastan",
            "ownerId": "6837907099"
          }
        ],
        "locationName": "Nazarbayev University",
        "locationId": "6000053",
        "ownerUsername": "sugirbaydastan",
        "ownerId": "6837907099",
        "isCommentsDisabled": false
      },
      {
        "id": "1692114637578155195",
        "type": "Sidecar",
        "shortCode": "Bd7mUw0FbS7",
        "caption": "@aset.eszhan -нын клипине тустим 📽📸🎥📹 youtube тан кориниздер😉",
        "hashtags": [],
        "mentions": [
          "aset.eszhan"
        ],
        "url": "https://www.instagram.com/p/Bd7mUw0FbS7/",
        "commentsCount": 5,
        "dimensionsHeight": 360,
        "dimensionsWidth": 640,
        "displayUrl": "https://instagram.fcgh3-1.fna.fbcdn.net/v/t51.2885-15/26151730_270547093476033_5660761136576856064_n.jpg?stp=dst-jpg_e35_tt6&_nc_ht=instagram.fcgh3-1.fna.fbcdn.net&_nc_cat=109&_nc_oc=Q6cZ2QF9sx0JDkrugwONNHmykgsO5mMA-Mci8Y6peX8Lbx1-6beXS5MWofDZ6xNi6TkiNqw&_nc_ohc=0A2SgXJ4UJ8Q7kNvwHB2woY&_nc_gid=Y1wez7Z7yzDjmAY2sS7_JA&edm=AOQ1c0wBAAAA&ccb=7-5&ig_cache_key=MTY5MjExMzk1NTIwNjg5MDgyNA%3D%3D.3-ccb7-5&oh=00_AfNjKFc_D3r6XSOjdn593u9p63BmWSI7E68tSywKmQisCQ&oe=68642616&_nc_sid=8b3546",
        "images": [
          "https://instagram.fcgh3-1.fna.fbcdn.net/v/t51.2885-15/26151730_270547093476033_5660761136576856064_n.jpg?stp=dst-jpg_e35_tt6&_nc_ht=instagram.fcgh3-1.fna.fbcdn.net&_nc_cat=109&_nc_oc=Q6cZ2QF9sx0JDkrugwONNHmykgsO5mMA-Mci8Y6peX8Lbx1-6beXS5MWofDZ6xNi6TkiNqw&_nc_ohc=0A2SgXJ4UJ8Q7kNvwHB2woY&_nc_gid=Y1wez7Z7yzDjmAY2sS7_JA&edm=AOQ1c0wBAAAA&ccb=7-5&ig_cache_key=MTY5MjExMzk1NTIwNjg5MDgyNA%3D%3D.3-ccb7-5&oh=00_AfNjKFc_D3r6XSOjdn593u9p63BmWSI7E68tSywKmQisCQ&oe=68642616&_nc_sid=8b3546",
          "https://instagram.fcgh3-2.fna.fbcdn.net/v/t51.2885-15/26156970_315812112272189_1570487223080452096_n.jpg?stp=dst-jpg_e35_tt6&_nc_ht=instagram.fcgh3-2.fna.fbcdn.net&_nc_cat=105&_nc_oc=Q6cZ2QF9sx0JDkrugwONNHmykgsO5mMA-Mci8Y6peX8Lbx1-6beXS5MWofDZ6xNi6TkiNqw&_nc_ohc=ve2Fcw6VIooQ7kNvwHFWmzJ&_nc_gid=Y1wez7Z7yzDjmAY2sS7_JA&edm=AOQ1c0wBAAAA&ccb=7-5&ig_cache_key=MTY5MjExNDA1NTkxMjExNTcwNA%3D%3D.3-ccb7-5&oh=00_AfND0H5uDcDcDRkwW8whyyozUAkksZzhlEJlR4re6CiSdQ&oe=68643EC8&_nc_sid=8b3546",
          "https://instagram.fcgh3-2.fna.fbcdn.net/v/t51.2885-15/26072658_1644123948996762_4607791651321020416_n.jpg?stp=dst-jpg_e35_tt6&_nc_ht=instagram.fcgh3-2.fna.fbcdn.net&_nc_cat=106&_nc_oc=Q6cZ2QF9sx0JDkrugwONNHmykgsO5mMA-Mci8Y6peX8Lbx1-6beXS5MWofDZ6xNi6TkiNqw&_nc_ohc=HqKPNDnp51QQ7kNvwHAAIRK&_nc_gid=Y1wez7Z7yzDjmAY2sS7_JA&edm=AOQ1c0wBAAAA&ccb=7-5&ig_cache_key=MTY5MjExNDA1NTMwODA3Mjk5NQ%3D%3D.3-ccb7-5&oh=00_AfPnquIoZ6BNiqfipvAaE1nda7wan7BbgNzmc9SZt-936A&oe=68642E81&_nc_sid=8b3546",
          "https://instagram.fcgh3-1.fna.fbcdn.net/v/t51.2885-15/26346687_166749530719019_2456687938595979264_n.jpg?stp=dst-jpg_e35_tt6&_nc_ht=instagram.fcgh3-1.fna.fbcdn.net&_nc_cat=111&_nc_oc=Q6cZ2QF9sx0JDkrugwONNHmykgsO5mMA-Mci8Y6peX8Lbx1-6beXS5MWofDZ6xNi6TkiNqw&_nc_ohc=EUjZIWNcmjgQ7kNvwHimuXR&_nc_gid=Y1wez7Z7yzDjmAY2sS7_JA&edm=AOQ1c0wBAAAA&ccb=7-5&ig_cache_key=MTY5MjExNDA1Njc0MjUxNzQyOQ%3D%3D.3-ccb7-5&oh=00_AfMME6WegqOsmCSWk_njIQqXyvyxfva4j_-AdBpaMXJx8Q&oe=686442A3&_nc_sid=8b3546"
        ],
        "alt": "Photo by Dastish on January 14, 2018.",
        "likesCount": 78,
        "timestamp": "2018-01-14T13:16:45.000Z",
        "childPosts": [
          {
            "id": "1692113955206890824",
            "type": "Image",
            "shortCode": "Bd7mK1TloVI",
            "caption": "",
            "hashtags": [],
            "mentions": [],
            "url": "https://www.instagram.com/p/Bd7mK1TloVI/",
            "commentsCount": 0,
            "firstComment": "",
            "latestComments": [],
            "dimensionsHeight": 360,
            "dimensionsWidth": 640,
            "displayUrl": "https://instagram.fcgh3-1.fna.fbcdn.net/v/t51.2885-15/26151730_270547093476033_5660761136576856064_n.jpg?stp=dst-jpg_e35_tt6&_nc_ht=instagram.fcgh3-1.fna.fbcdn.net&_nc_cat=109&_nc_oc=Q6cZ2QF9sx0JDkrugwONNHmykgsO5mMA-Mci8Y6peX8Lbx1-6beXS5MWofDZ6xNi6TkiNqw&_nc_ohc=0A2SgXJ4UJ8Q7kNvwHB2woY&_nc_gid=Y1wez7Z7yzDjmAY2sS7_JA&edm=AOQ1c0wBAAAA&ccb=7-5&ig_cache_key=MTY5MjExMzk1NTIwNjg5MDgyNA%3D%3D.3-ccb7-5&oh=00_AfNjKFc_D3r6XSOjdn593u9p63BmWSI7E68tSywKmQisCQ&oe=68642616&_nc_sid=8b3546",
            "images": [],
            "alt": "Photo by Dastish on January 14, 2018.",
            "likesCount": null,
            "timestamp": null,
            "childPosts": [],
            "ownerUsername": "sugirbaydastan",
            "ownerId": "6837907099"
          },
          {
            "id": "1692114055912115704",
            "type": "Image",
            "shortCode": "Bd7mMTGFk34",
            "caption": "",
            "hashtags": [],
            "mentions": [],
            "url": "https://www.instagram.com/p/Bd7mMTGFk34/",
            "commentsCount": 0,
            "firstComment": "",
            "latestComments": [],
            "dimensionsHeight": 426,
            "dimensionsWidth": 750,
            "displayUrl": "https://instagram.fcgh3-2.fna.fbcdn.net/v/t51.2885-15/26156970_315812112272189_1570487223080452096_n.jpg?stp=dst-jpg_e35_tt6&_nc_ht=instagram.fcgh3-2.fna.fbcdn.net&_nc_cat=105&_nc_oc=Q6cZ2QF9sx0JDkrugwONNHmykgsO5mMA-Mci8Y6peX8Lbx1-6beXS5MWofDZ6xNi6TkiNqw&_nc_ohc=ve2Fcw6VIooQ7kNvwHFWmzJ&_nc_gid=Y1wez7Z7yzDjmAY2sS7_JA&edm=AOQ1c0wBAAAA&ccb=7-5&ig_cache_key=MTY5MjExNDA1NTkxMjExNTcwNA%3D%3D.3-ccb7-5&oh=00_AfND0H5uDcDcDRkwW8whyyozUAkksZzhlEJlR4re6CiSdQ&oe=68643EC8&_nc_sid=8b3546",
            "images": [],
            "alt": "Photo by Dastish on January 14, 2018.",
            "likesCount": null,
            "timestamp": null,
            "childPosts": [],
            "ownerUsername": "sugirbaydastan",
            "ownerId": "6837907099"
          },
          {
            "id": "1692114055308072995",
            "type": "Image",
            "shortCode": "Bd7mMSiFVgj",
            "caption": "",
            "hashtags": [],
            "mentions": [],
            "url": "https://www.instagram.com/p/Bd7mMSiFVgj/",
            "commentsCount": 0,
            "firstComment": "",
            "latestComments": [],
            "dimensionsHeight": 426,
            "dimensionsWidth": 750,
            "displayUrl": "https://instagram.fcgh3-2.fna.fbcdn.net/v/t51.2885-15/26072658_1644123948996762_4607791651321020416_n.jpg?stp=dst-jpg_e35_tt6&_nc_ht=instagram.fcgh3-2.fna.fbcdn.net&_nc_cat=106&_nc_oc=Q6cZ2QF9sx0JDkrugwONNHmykgsO5mMA-Mci8Y6peX8Lbx1-6beXS5MWofDZ6xNi6TkiNqw&_nc_ohc=HqKPNDnp51QQ7kNvwHAAIRK&_nc_gid=Y1wez7Z7yzDjmAY2sS7_JA&edm=AOQ1c0wBAAAA&ccb=7-5&ig_cache_key=MTY5MjExNDA1NTMwODA3Mjk5NQ%3D%3D.3-ccb7-5&oh=00_AfPnquIoZ6BNiqfipvAaE1nda7wan7BbgNzmc9SZt-936A&oe=68642E81&_nc_sid=8b3546",
            "images": [],
            "alt": "Photo by Dastish on January 14, 2018.",
            "likesCount": null,
            "timestamp": null,
            "childPosts": [],
            "ownerUsername": "sugirbaydastan",
            "ownerId": "6837907099"
          },
          {
            "id": "1692114056742517429",
            "type": "Image",
            "shortCode": "Bd7mMT3lTq1",
            "caption": "",
            "hashtags": [],
            "mentions": [],
            "url": "https://www.instagram.com/p/Bd7mMT3lTq1/",
            "commentsCount": 0,
            "firstComment": "",
            "latestComments": [],
            "dimensionsHeight": 426,
            "dimensionsWidth": 750,
            "displayUrl": "https://instagram.fcgh3-1.fna.fbcdn.net/v/t51.2885-15/26346687_166749530719019_2456687938595979264_n.jpg?stp=dst-jpg_e35_tt6&_nc_ht=instagram.fcgh3-1.fna.fbcdn.net&_nc_cat=111&_nc_oc=Q6cZ2QF9sx0JDkrugwONNHmykgsO5mMA-Mci8Y6peX8Lbx1-6beXS5MWofDZ6xNi6TkiNqw&_nc_ohc=EUjZIWNcmjgQ7kNvwHimuXR&_nc_gid=Y1wez7Z7yzDjmAY2sS7_JA&edm=AOQ1c0wBAAAA&ccb=7-5&ig_cache_key=MTY5MjExNDA1Njc0MjUxNzQyOQ%3D%3D.3-ccb7-5&oh=00_AfMME6WegqOsmCSWk_njIQqXyvyxfva4j_-AdBpaMXJx8Q&oe=686442A3&_nc_sid=8b3546",
            "images": [],
            "alt": "Photo by Dastish on January 14, 2018.",
            "likesCount": null,
            "timestamp": null,
            "childPosts": [],
            "ownerUsername": "sugirbaydastan",
            "ownerId": "6837907099"
          }
        ],
        "ownerUsername": "sugirbaydastan",
        "ownerId": "6837907099",
        "isCommentsDisabled": false
      },
      {
        "id": "1692044922910447138",
        "type": "Sidecar",
        "shortCode": "Bd7WeR-FJYi",
        "caption": "баттуттан абден секирдим😉💫",
        "hashtags": [],
        "mentions": [],
        "url": "https://www.instagram.com/p/Bd7WeR-FJYi/",
        "commentsCount": 2,
        "dimensionsHeight": 1080,
        "dimensionsWidth": 1080,
        "displayUrl": "https://instagram.fcgh3-1.fna.fbcdn.net/v/t51.2885-15/26267086_180793295846735_3836645451738644480_n.jpg?se=7&stp=dst-jpg_e35_tt6&_nc_ht=instagram.fcgh3-1.fna.fbcdn.net&_nc_cat=111&_nc_oc=Q6cZ2QF9sx0JDkrugwONNHmykgsO5mMA-Mci8Y6peX8Lbx1-6beXS5MWofDZ6xNi6TkiNqw&_nc_ohc=FBOXUddnWWkQ7kNvwGEHXG7&_nc_gid=Y1wez7Z7yzDjmAY2sS7_JA&edm=AOQ1c0wBAAAA&ccb=7-5&ig_cache_key=MTY5MjA0NDQxNTM0OTQ1ODM2OQ%3D%3D.3-ccb7-5&oh=00_AfOJp2M2H4tayMqiotj0qhaa6iXMZAMudoYTSzRODBx-Rw&oe=68642DE5&_nc_sid=8b3546",
        "images": [
          "https://instagram.fcgh3-1.fna.fbcdn.net/v/t51.2885-15/26267086_180793295846735_3836645451738644480_n.jpg?se=7&stp=dst-jpg_e35_tt6&_nc_ht=instagram.fcgh3-1.fna.fbcdn.net&_nc_cat=111&_nc_oc=Q6cZ2QF9sx0JDkrugwONNHmykgsO5mMA-Mci8Y6peX8Lbx1-6beXS5MWofDZ6xNi6TkiNqw&_nc_ohc=FBOXUddnWWkQ7kNvwGEHXG7&_nc_gid=Y1wez7Z7yzDjmAY2sS7_JA&edm=AOQ1c0wBAAAA&ccb=7-5&ig_cache_key=MTY5MjA0NDQxNTM0OTQ1ODM2OQ%3D%3D.3-ccb7-5&oh=00_AfOJp2M2H4tayMqiotj0qhaa6iXMZAMudoYTSzRODBx-Rw&oe=68642DE5&_nc_sid=8b3546",
          "https://instagram.fcgh3-2.fna.fbcdn.net/v/t51.2885-15/26071905_162499921120107_2911855052069011456_n.jpg?se=7&stp=dst-jpg_e35_tt6&_nc_ht=instagram.fcgh3-2.fna.fbcdn.net&_nc_cat=103&_nc_oc=Q6cZ2QF9sx0JDkrugwONNHmykgsO5mMA-Mci8Y6peX8Lbx1-6beXS5MWofDZ6xNi6TkiNqw&_nc_ohc=hHffOjauH_kQ7kNvwEBytoE&_nc_gid=Y1wez7Z7yzDjmAY2sS7_JA&edm=AOQ1c0wBAAAA&ccb=7-5&ig_cache_key=MTY5MjA0NDQ1NzE4MzQ0MDg3NA%3D%3D.3-ccb7-5&oh=00_AfNc2buIdFwsK7fuDOi3qwZf9CcEQbqstFh-skYZuUqXzw&oe=68642429&_nc_sid=8b3546",
          "https://instagram.fcgh3-2.fna.fbcdn.net/v/t51.2885-15/26073430_138882346789434_3193747594090119168_n.jpg?se=7&stp=dst-jpg_e35_tt6&_nc_ht=instagram.fcgh3-2.fna.fbcdn.net&_nc_cat=106&_nc_oc=Q6cZ2QF9sx0JDkrugwONNHmykgsO5mMA-Mci8Y6peX8Lbx1-6beXS5MWofDZ6xNi6TkiNqw&_nc_ohc=prkkzmSxQGwQ7kNvwFb6nIw&_nc_gid=Y1wez7Z7yzDjmAY2sS7_JA&edm=AOQ1c0wBAAAA&ccb=7-5&ig_cache_key=MTY5MjA0NDQ3OTM5NjUyODE0OA%3D%3D.3-ccb7-5&oh=00_AfNclA2GbVR97uUQGOevX2qJvE-KhVEFKIAJCKX9APsbPg&oe=68643CA9&_nc_sid=8b3546",
          "https://instagram.fcgh3-1.fna.fbcdn.net/v/t51.2885-15/26070967_187635475314777_2317077514083631104_n.jpg?stp=dst-jpg_e15_tt6&_nc_ht=instagram.fcgh3-1.fna.fbcdn.net&_nc_cat=109&_nc_oc=Q6cZ2QF9sx0JDkrugwONNHmykgsO5mMA-Mci8Y6peX8Lbx1-6beXS5MWofDZ6xNi6TkiNqw&_nc_ohc=0JDYn_p9pC8Q7kNvwFHSG5J&_nc_gid=Y1wez7Z7yzDjmAY2sS7_JA&edm=AOQ1c0wBAAAA&ccb=7-5&oh=00_AfPV6aQRAyWQ5owjrJuzTbr48qeOwjaco_mLUTPmbR2Wdw&oe=686437AE&_nc_sid=8b3546"
        ],
        "alt": "Photo by Dastish on January 14, 2018.",
        "likesCount": 53,
        "timestamp": "2018-01-14T10:58:14.000Z",
        "childPosts": [
          {
            "id": "1692044415349458369",
            "type": "Image",
            "shortCode": "Bd7WW5RFoXB",
            "caption": "",
            "hashtags": [],
            "mentions": [],
            "url": "https://www.instagram.com/p/Bd7WW5RFoXB/",
            "commentsCount": 0,
            "firstComment": "",
            "latestComments": [],
            "dimensionsHeight": 1080,
            "dimensionsWidth": 1080,
            "displayUrl": "https://instagram.fcgh3-1.fna.fbcdn.net/v/t51.2885-15/26267086_180793295846735_3836645451738644480_n.jpg?se=7&stp=dst-jpg_e35_tt6&_nc_ht=instagram.fcgh3-1.fna.fbcdn.net&_nc_cat=111&_nc_oc=Q6cZ2QF9sx0JDkrugwONNHmykgsO5mMA-Mci8Y6peX8Lbx1-6beXS5MWofDZ6xNi6TkiNqw&_nc_ohc=FBOXUddnWWkQ7kNvwGEHXG7&_nc_gid=Y1wez7Z7yzDjmAY2sS7_JA&edm=AOQ1c0wBAAAA&ccb=7-5&ig_cache_key=MTY5MjA0NDQxNTM0OTQ1ODM2OQ%3D%3D.3-ccb7-5&oh=00_AfOJp2M2H4tayMqiotj0qhaa6iXMZAMudoYTSzRODBx-Rw&oe=68642DE5&_nc_sid=8b3546",
            "images": [],
            "alt": "Photo by Dastish on January 14, 2018.",
            "likesCount": null,
            "timestamp": null,
            "childPosts": [],
            "ownerUsername": "sugirbaydastan",
            "ownerId": "6837907099"
          },
          {
            "id": "1692044457183440874",
            "type": "Image",
            "shortCode": "Bd7WXgOlm_q",
            "caption": "",
            "hashtags": [],
            "mentions": [],
            "url": "https://www.instagram.com/p/Bd7WXgOlm_q/",
            "commentsCount": 0,
            "firstComment": "",
            "latestComments": [],
            "dimensionsHeight": 1080,
            "dimensionsWidth": 1080,
            "displayUrl": "https://instagram.fcgh3-2.fna.fbcdn.net/v/t51.2885-15/26071905_162499921120107_2911855052069011456_n.jpg?se=7&stp=dst-jpg_e35_tt6&_nc_ht=instagram.fcgh3-2.fna.fbcdn.net&_nc_cat=103&_nc_oc=Q6cZ2QF9sx0JDkrugwONNHmykgsO5mMA-Mci8Y6peX8Lbx1-6beXS5MWofDZ6xNi6TkiNqw&_nc_ohc=hHffOjauH_kQ7kNvwEBytoE&_nc_gid=Y1wez7Z7yzDjmAY2sS7_JA&edm=AOQ1c0wBAAAA&ccb=7-5&ig_cache_key=MTY5MjA0NDQ1NzE4MzQ0MDg3NA%3D%3D.3-ccb7-5&oh=00_AfNc2buIdFwsK7fuDOi3qwZf9CcEQbqstFh-skYZuUqXzw&oe=68642429&_nc_sid=8b3546",
            "images": [],
            "alt": "Photo by Dastish on January 14, 2018.",
            "likesCount": null,
            "timestamp": null,
            "childPosts": [],
            "ownerUsername": "sugirbaydastan",
            "ownerId": "6837907099"
          },
          {
            "id": "1692044479396528148",
            "type": "Image",
            "shortCode": "Bd7WX06l0AU",
            "caption": "",
            "hashtags": [],
            "mentions": [],
            "url": "https://www.instagram.com/p/Bd7WX06l0AU/",
            "commentsCount": 0,
            "firstComment": "",
            "latestComments": [],
            "dimensionsHeight": 1080,
            "dimensionsWidth": 1080,
            "displayUrl": "https://instagram.fcgh3-2.fna.fbcdn.net/v/t51.2885-15/26073430_138882346789434_3193747594090119168_n.jpg?se=7&stp=dst-jpg_e35_tt6&_nc_ht=instagram.fcgh3-2.fna.fbcdn.net&_nc_cat=106&_nc_oc=Q6cZ2QF9sx0JDkrugwONNHmykgsO5mMA-Mci8Y6peX8Lbx1-6beXS5MWofDZ6xNi6TkiNqw&_nc_ohc=prkkzmSxQGwQ7kNvwFb6nIw&_nc_gid=Y1wez7Z7yzDjmAY2sS7_JA&edm=AOQ1c0wBAAAA&ccb=7-5&ig_cache_key=MTY5MjA0NDQ3OTM5NjUyODE0OA%3D%3D.3-ccb7-5&oh=00_AfNclA2GbVR97uUQGOevX2qJvE-KhVEFKIAJCKX9APsbPg&oe=68643CA9&_nc_sid=8b3546",
            "images": [],
            "alt": "Photo by Dastish on January 14, 2018.",
            "likesCount": null,
            "timestamp": null,
            "childPosts": [],
            "ownerUsername": "sugirbaydastan",
            "ownerId": "6837907099"
          },
          {
            "id": "1692044433997386435",
            "type": "Video",
            "shortCode": "Bd7WXKol1LD",
            "caption": "",
            "hashtags": [],
            "mentions": [],
            "url": "https://www.instagram.com/p/Bd7WXKol1LD/",
            "commentsCount": 0,
            "firstComment": "",
            "latestComments": [],
            "dimensionsHeight": 750,
            "dimensionsWidth": 750,
            "displayUrl": "https://instagram.fcgh3-1.fna.fbcdn.net/v/t51.2885-15/26070967_187635475314777_2317077514083631104_n.jpg?stp=dst-jpg_e15_tt6&_nc_ht=instagram.fcgh3-1.fna.fbcdn.net&_nc_cat=109&_nc_oc=Q6cZ2QF9sx0JDkrugwONNHmykgsO5mMA-Mci8Y6peX8Lbx1-6beXS5MWofDZ6xNi6TkiNqw&_nc_ohc=0JDYn_p9pC8Q7kNvwFHSG5J&_nc_gid=Y1wez7Z7yzDjmAY2sS7_JA&edm=AOQ1c0wBAAAA&ccb=7-5&oh=00_AfPV6aQRAyWQ5owjrJuzTbr48qeOwjaco_mLUTPmbR2Wdw&oe=686437AE&_nc_sid=8b3546",
            "images": [],
            "videoUrl": "https://instagram.fcgh3-1.fna.fbcdn.net/o1/v/t16/f2/m84/AQMugYrnhnVRRkWdBvvR3oL_xIpOvikAxWduM0vlFByS5ofvYZYh8tGjcVBISIkn0n5EPRxXFu4q5uX47w-aopjBR-3llopPJX0IKv0.mp4?stp=dst-mp4&efg=eyJxZV9ncm91cHMiOiJbXCJpZ193ZWJfZGVsaXZlcnlfdnRzX290ZlwiXSIsInZlbmNvZGVfdGFnIjoidnRzX3ZvZF91cmxnZW4uY2Fyb3VzZWxfaXRlbS5jMi42NDAuYmFzZWxpbmUifQ&_nc_cat=104&vs=486555554248867_2912265477&_nc_vs=HBksFQIYTGlnX2JhY2tmaWxsX3RpbWVsaW5lX3ZvZC8zRDQzOTI0MDBCM0YxQUIyQTJENzg1MjYzQ0JFREJBNl92aWRlb19kYXNoaW5pdC5tcDQVAALIARIAFQIYOnBhc3N0aHJvdWdoX2V2ZXJzdG9yZS9HRjRtWkJ0TUplR1VlaHNjQUx2X20wSngyLXcxYnBrd0FBQUYVAgLIARIAKAAYABsAFQAAJvD%2B04X5voYBFQIoAkMzLBdAJLtkWhysCBgSZGFzaF9iYXNlbGluZV8xX3YxEQB17gdl8J0BAA%3D%3D&ccb=9-4&oh=00_AfP8_0P4jmeHhEX9boMTF2v2TUbQe9FCKL25pAayjC6iXA&oe=686025AA&_nc_sid=8b3546",
            "alt": null,
            "likesCount": null,
            "videoViewCount": 248,
            "timestamp": null,
            "childPosts": [],
            "ownerUsername": "sugirbaydastan",
            "ownerId": "6837907099"
          }
        ],
        "ownerUsername": "sugirbaydastan",
        "ownerId": "6837907099",
        "isCommentsDisabled": false
      },
      {
        "id": "1692043314554320519",
        "type": "Image",
        "shortCode": "Bd7WG4ElbaH",
        "caption": "👦🏻⚔️ #Дастан",
        "hashtags": [
          "Дастан"
        ],
        "mentions": [],
        "url": "https://www.instagram.com/p/Bd7WG4ElbaH/",
        "commentsCount": 4,
        "dimensionsHeight": 1080,
        "dimensionsWidth": 1080,
        "displayUrl": "https://instagram.fcgh3-2.fna.fbcdn.net/v/t51.2885-15/26181025_999679783514118_8961719558280839168_n.jpg?se=7&stp=dst-jpg_e35_tt6&_nc_ht=instagram.fcgh3-2.fna.fbcdn.net&_nc_cat=106&_nc_oc=Q6cZ2QF9sx0JDkrugwONNHmykgsO5mMA-Mci8Y6peX8Lbx1-6beXS5MWofDZ6xNi6TkiNqw&_nc_ohc=uP2N-thJFk4Q7kNvwGBHUbk&_nc_gid=Y1wez7Z7yzDjmAY2sS7_JA&edm=AOQ1c0wBAAAA&ccb=7-5&ig_cache_key=MTY5MjA0MzMxNDU1NDMyMDUxOQ%3D%3D.3-ccb7-5&oh=00_AfOGIswd00Pdo0a6xwSF9kRliUYovmoWwNYFTgMF4MIFtA&oe=6864189E&_nc_sid=8b3546",
        "images": [],
        "alt": "Photo by Dastish on January 14, 2018.",
        "likesCount": 56,
        "timestamp": "2018-01-14T10:55:03.000Z",
        "childPosts": [],
        "ownerUsername": "sugirbaydastan",
        "ownerId": "6837907099",
        "isCommentsDisabled": false
      },
      {
        "id": "1681826390314602916",
        "type": "Image",
        "shortCode": "BdXDDD4lFGk",
        "caption": "hello instagram🙋🏻‍♂️",
        "hashtags": [],
        "mentions": [],
        "url": "https://www.instagram.com/p/BdXDDD4lFGk/",
        "commentsCount": 2,
        "dimensionsHeight": 1080,
        "dimensionsWidth": 1080,
        "displayUrl": "https://instagram.fcgh3-1.fna.fbcdn.net/v/t51.2885-15/26066663_366890923720768_6278681298382880768_n.jpg?se=7&stp=dst-jpg_e35_tt6&_nc_ht=instagram.fcgh3-1.fna.fbcdn.net&_nc_cat=104&_nc_oc=Q6cZ2QF9sx0JDkrugwONNHmykgsO5mMA-Mci8Y6peX8Lbx1-6beXS5MWofDZ6xNi6TkiNqw&_nc_ohc=tQOye650H20Q7kNvwGCrRpc&_nc_gid=Y1wez7Z7yzDjmAY2sS7_JA&edm=AOQ1c0wBAAAA&ccb=7-5&ig_cache_key=MTY4MTgyNjM5MDMxNDYwMjkxNg%3D%3D.3-ccb7-5&oh=00_AfPkh47laBCDjPldnQ5AIUFbZJXzM4kRUG_64Yfjmz0L9Q&oe=686435D4&_nc_sid=8b3546",
        "images": [],
        "alt": "Photo by Dastish on December 31, 2017.",
        "likesCount": 58,
        "timestamp": "2017-12-31T08:35:50.000Z",
        "childPosts": [],
        "ownerUsername": "sugirbaydastan",
        "ownerId": "6837907099",
        "isCommentsDisabled": false
      }
    ],
    "fbid": "17841406812984738"
  }
]